nanoppo/__init__.py
nanoppo/checkpoint_manager.py
nanoppo/continuous_action_ppo.py
nanoppo/continuous_action_ppo_v2.py
nanoppo/cosine_lr_scheduler.py
nanoppo/discrete_action_ppo.py
nanoppo/environment_manager.py
nanoppo/envs/point_mass1d.py
nanoppo/envs/point_mass2d.py
nanoppo/evaluation.py
nanoppo/metrics_recorder.py
nanoppo/network_manager.py
nanoppo/normalizer.py
nanoppo/policy/actor_critic.py
nanoppo/policy/actor_critic_causal_attention.py
nanoppo/policy/network.py
nanoppo/ppo_agent.py
nanoppo/ppo_utils.py
nanoppo/random_utils.py
nanoppo/reward_scaler.py
nanoppo/reward_shaper.py
nanoppo/rollout_buffer.py
nanoppo/sinusoidal_positional_encoding.py
nanoppo/state_scaler.py
nanoppo/train_ppo_agent.py
nanoppo/tune_continuous_action_ppo.py
nanoppo/utils.py
nanoppo/wandb_logger.py
nanoppo-0.15.post2.dist-info/LICENSE
nanoppo-0.15.post2.dist-info/METADATA
nanoppo-0.15.post2.dist-info/WHEEL
nanoppo-0.15.post2.dist-info/RECORD
